{
  "auto-program": {
    "naziv": "auto program",
    "caption": "\"Neque porro quisquam est qui dolorem ipsum quia dolor sit amet, consectetur, adipisci velit...\"",
    "desc": "dasdasdas",
    "slug": "auto-program",
    "kategorije": {
      "gume": {
        "slug": "gume",
        "naziv": "Gume",
        "caption": "dsa",
        "desc": "sadas",
        "prozivodi": {},
        "image": "http://localhost:3001/uploads/category/gume.jpg",
        "imageName": "gume.jpg"
      }
    },
    "imageName": "auto-program.jpg",
    "image": "https://api.auto-delovi-3sp.com/uploads/program/auto-program.jpg"
  },
  "traktorski-program": {
    "naziv": "traktorski program",
    "caption": "\"Neque porro quisquam est qui dolorem ipsum quia dolor sit amet, consectetur, adipisci velit...\"",
    "desc": "dasdas",
    "slug": "traktorski-program",
    "kategorije": {},
    "imageName": "traktorski-program.jpg",
    "image": "https://api.auto-delovi-3sp.com/uploads/program/traktorski-program.jpg"
  }
}